{
  "type": "component",
  "metadata": {},
  "schema": {
    "name": "slider",
    "friendlyName": "slider",
    "description": "A value slider",
    "icon": "Text",
    "settings": [
      {
        "type": "number",
        "key": "value",
        "label": "Value"
      },
      {
        "type": "number",
        "key": "min",
        "label": "Minimum"
      },
      {
        "type": "number",
        "key": "max",
        "label": "Maximum"
      },
      {
        "type": "number",
        "key": "step",
        "label": "Step"
      }
    ]
  }
}